{
  "general": {
    "T_sim": 5,
    "T_compute": 0.0225433,
    "dt": 0.1,
    "n_dt/T_compute": 2217.9538931744687
  },
  "ConstantWind.step": {
    "total_s": 1.42e-05,
    "count": 51
  },
  "Aerodynamics.step": {
    "total_s": 0.0225055,
    "count": 51,
    "Aerodynamics.step_inflow": {
      "total_s": 0.014155,
      "count": 51,
      "ConstantWind.__call__": {
        "total_s": 0.0027219,
        "count": 153
      }
    },
    "Aerodynamics.step_forces": {
      "total_s": 0.0061465,
      "count": 51
    },
    "Aerodynamics.step_induction": {
      "total_s": 0.0020032,
      "count": 51
    }
  },
  "RigidStructure.step": {
    "total_s": 2.36e-05,
    "count": 51
  }
}